[
  {
    "width": 800,
    "height": 1139,
    "type": "webp",
    "mime": "image/webp",
    "wUnits": "px",
    "hUnits": "px",
    "length": 159360,
    "url": "https://cdn.black-clover.org/file/flanbox/failure-frame/chapter-12/1.webp"
  },
  {
    "width": 800,
    "height": 1139,
    "type": "webp",
    "mime": "image/webp",
    "wUnits": "px",
    "hUnits": "px",
    "length": 180012,
    "url": "https://cdn.black-clover.org/file/flanbox/failure-frame/chapter-12/2.webp"
  },
  {
    "width": 800,
    "height": 1139,
    "type": "webp",
    "mime": "image/webp",
    "wUnits": "px",
    "hUnits": "px",
    "length": 194114,
    "url": "https://cdn.black-clover.org/file/flanbox/failure-frame/chapter-12/3.webp"
  },
  {
    "width": 800,
    "height": 1139,
    "type": "webp",
    "mime": "image/webp",
    "wUnits": "px",
    "hUnits": "px",
    "length": 244368,
    "url": "https://cdn.black-clover.org/file/flanbox/failure-frame/chapter-12/4.webp"
  },
  {
    "width": 800,
    "height": 1139,
    "type": "webp",
    "mime": "image/webp",
    "wUnits": "px",
    "hUnits": "px",
    "length": 233158,
    "url": "https://cdn.black-clover.org/file/flanbox/failure-frame/chapter-12/5.webp"
  },
  {
    "width": 800,
    "height": 1139,
    "type": "webp",
    "mime": "image/webp",
    "wUnits": "px",
    "hUnits": "px",
    "length": 200606,
    "url": "https://cdn.black-clover.org/file/flanbox/failure-frame/chapter-12/6.webp"
  },
  {
    "width": 800,
    "height": 1139,
    "type": "webp",
    "mime": "image/webp",
    "wUnits": "px",
    "hUnits": "px",
    "length": 211562,
    "url": "https://cdn.black-clover.org/file/flanbox/failure-frame/chapter-12/7.webp"
  },
  {
    "width": 800,
    "height": 1139,
    "type": "webp",
    "mime": "image/webp",
    "wUnits": "px",
    "hUnits": "px",
    "length": 254360,
    "url": "https://cdn.black-clover.org/file/flanbox/failure-frame/chapter-12/8.webp"
  },
  {
    "width": 800,
    "height": 1139,
    "type": "webp",
    "mime": "image/webp",
    "wUnits": "px",
    "hUnits": "px",
    "length": 169684,
    "url": "https://cdn.black-clover.org/file/flanbox/failure-frame/chapter-12/9.webp"
  },
  {
    "width": 800,
    "height": 569,
    "type": "webp",
    "mime": "image/webp",
    "wUnits": "px",
    "hUnits": "px",
    "length": 137292,
    "url": "https://cdn.black-clover.org/file/flanbox/failure-frame/chapter-12/10.webp"
  },
  {
    "width": 800,
    "height": 1139,
    "type": "webp",
    "mime": "image/webp",
    "wUnits": "px",
    "hUnits": "px",
    "length": 255260,
    "url": "https://cdn.black-clover.org/file/flanbox/failure-frame/chapter-12/11.webp"
  },
  {
    "width": 800,
    "height": 1139,
    "type": "webp",
    "mime": "image/webp",
    "wUnits": "px",
    "hUnits": "px",
    "length": 165906,
    "url": "https://cdn.black-clover.org/file/flanbox/failure-frame/chapter-12/12.webp"
  },
  {
    "width": 800,
    "height": 1139,
    "type": "webp",
    "mime": "image/webp",
    "wUnits": "px",
    "hUnits": "px",
    "length": 204782,
    "url": "https://cdn.black-clover.org/file/flanbox/failure-frame/chapter-12/13.webp"
  },
  {
    "width": 800,
    "height": 1139,
    "type": "webp",
    "mime": "image/webp",
    "wUnits": "px",
    "hUnits": "px",
    "length": 160140,
    "url": "https://cdn.black-clover.org/file/flanbox/failure-frame/chapter-12/14.webp"
  },
  {
    "width": 800,
    "height": 1139,
    "type": "webp",
    "mime": "image/webp",
    "wUnits": "px",
    "hUnits": "px",
    "length": 218536,
    "url": "https://cdn.black-clover.org/file/flanbox/failure-frame/chapter-12/15.webp"
  },
  {
    "width": 800,
    "height": 1139,
    "type": "webp",
    "mime": "image/webp",
    "wUnits": "px",
    "hUnits": "px",
    "length": 122550,
    "url": "https://cdn.black-clover.org/file/flanbox/failure-frame/chapter-12/16.webp"
  },
  {
    "width": 800,
    "height": 1139,
    "type": "webp",
    "mime": "image/webp",
    "wUnits": "px",
    "hUnits": "px",
    "length": 176606,
    "url": "https://cdn.black-clover.org/file/flanbox/failure-frame/chapter-12/17.webp"
  },
  {
    "width": 800,
    "height": 1139,
    "type": "webp",
    "mime": "image/webp",
    "wUnits": "px",
    "hUnits": "px",
    "length": 155894,
    "url": "https://cdn.black-clover.org/file/flanbox/failure-frame/chapter-12/18.webp"
  },
  {
    "width": 800,
    "height": 1139,
    "type": "webp",
    "mime": "image/webp",
    "wUnits": "px",
    "hUnits": "px",
    "length": 122212,
    "url": "https://cdn.black-clover.org/file/flanbox/failure-frame/chapter-12/19.webp"
  },
  {
    "width": 800,
    "height": 1139,
    "type": "webp",
    "mime": "image/webp",
    "wUnits": "px",
    "hUnits": "px",
    "length": 150928,
    "url": "https://cdn.black-clover.org/file/flanbox/failure-frame/chapter-12/20.webp"
  },
  {
    "width": 800,
    "height": 1139,
    "type": "webp",
    "mime": "image/webp",
    "wUnits": "px",
    "hUnits": "px",
    "length": 162790,
    "url": "https://cdn.black-clover.org/file/flanbox/failure-frame/chapter-12/21.webp"
  },
  {
    "width": 800,
    "height": 1139,
    "type": "webp",
    "mime": "image/webp",
    "wUnits": "px",
    "hUnits": "px",
    "length": 258546,
    "url": "https://cdn.black-clover.org/file/flanbox/failure-frame/chapter-12/22.webp"
  },
  {
    "width": 800,
    "height": 1139,
    "type": "webp",
    "mime": "image/webp",
    "wUnits": "px",
    "hUnits": "px",
    "length": 113876,
    "url": "https://cdn.black-clover.org/file/flanbox/failure-frame/chapter-12/23.webp"
  },
  {
    "width": 800,
    "height": 1139,
    "type": "webp",
    "mime": "image/webp",
    "wUnits": "px",
    "hUnits": "px",
    "length": 172878,
    "url": "https://cdn.black-clover.org/file/flanbox/failure-frame/chapter-12/24.webp"
  },
  {
    "width": 800,
    "height": 1139,
    "type": "webp",
    "mime": "image/webp",
    "wUnits": "px",
    "hUnits": "px",
    "length": 179698,
    "url": "https://cdn.black-clover.org/file/flanbox/failure-frame/chapter-12/25.webp"
  },
  {
    "width": 800,
    "height": 1139,
    "type": "webp",
    "mime": "image/webp",
    "wUnits": "px",
    "hUnits": "px",
    "length": 183038,
    "url": "https://cdn.black-clover.org/file/flanbox/failure-frame/chapter-12/26.webp"
  },
  {
    "width": 800,
    "height": 1139,
    "type": "webp",
    "mime": "image/webp",
    "wUnits": "px",
    "hUnits": "px",
    "length": 207052,
    "url": "https://cdn.black-clover.org/file/flanbox/failure-frame/chapter-12/27.webp"
  },
  {
    "width": 800,
    "height": 1139,
    "type": "webp",
    "mime": "image/webp",
    "wUnits": "px",
    "hUnits": "px",
    "length": 200962,
    "url": "https://cdn.black-clover.org/file/flanbox/failure-frame/chapter-12/28.webp"
  },
  {
    "width": 800,
    "height": 1139,
    "type": "webp",
    "mime": "image/webp",
    "wUnits": "px",
    "hUnits": "px",
    "length": 210638,
    "url": "https://cdn.black-clover.org/file/flanbox/failure-frame/chapter-12/29.webp"
  },
  {
    "width": 800,
    "height": 1139,
    "type": "webp",
    "mime": "image/webp",
    "wUnits": "px",
    "hUnits": "px",
    "length": 215948,
    "url": "https://cdn.black-clover.org/file/flanbox/failure-frame/chapter-12/30.webp"
  },
  {
    "width": 800,
    "height": 1139,
    "type": "webp",
    "mime": "image/webp",
    "wUnits": "px",
    "hUnits": "px",
    "length": 243778,
    "url": "https://cdn.black-clover.org/file/flanbox/failure-frame/chapter-12/31.webp"
  },
  {
    "width": 800,
    "height": 1139,
    "type": "webp",
    "mime": "image/webp",
    "wUnits": "px",
    "hUnits": "px",
    "length": 184966,
    "url": "https://cdn.black-clover.org/file/flanbox/failure-frame/chapter-12/32.webp"
  }
]