[
  {
    "width": 800,
    "height": 800,
    "type": "webp",
    "mime": "image/webp",
    "wUnits": "px",
    "hUnits": "px",
    "length": 91994,
    "url": "https://cdn.black-clover.org/file/flanbox/failure-frame/chapter-45.2/1.webp"
  },
  {
    "width": 800,
    "height": 1137,
    "type": "webp",
    "mime": "image/webp",
    "wUnits": "px",
    "hUnits": "px",
    "length": 167474,
    "url": "https://cdn.black-clover.org/file/flanbox/failure-frame/chapter-45.2/2.webp"
  },
  {
    "width": 800,
    "height": 1137,
    "type": "webp",
    "mime": "image/webp",
    "wUnits": "px",
    "hUnits": "px",
    "length": 129466,
    "url": "https://cdn.black-clover.org/file/flanbox/failure-frame/chapter-45.2/3.webp"
  },
  {
    "width": 800,
    "height": 1137,
    "type": "webp",
    "mime": "image/webp",
    "wUnits": "px",
    "hUnits": "px",
    "length": 126184,
    "url": "https://cdn.black-clover.org/file/flanbox/failure-frame/chapter-45.2/4.webp"
  },
  {
    "width": 800,
    "height": 1137,
    "type": "webp",
    "mime": "image/webp",
    "wUnits": "px",
    "hUnits": "px",
    "length": 115410,
    "url": "https://cdn.black-clover.org/file/flanbox/failure-frame/chapter-45.2/5.webp"
  },
  {
    "width": 800,
    "height": 1137,
    "type": "webp",
    "mime": "image/webp",
    "wUnits": "px",
    "hUnits": "px",
    "length": 123110,
    "url": "https://cdn.black-clover.org/file/flanbox/failure-frame/chapter-45.2/6.webp"
  },
  {
    "width": 800,
    "height": 1137,
    "type": "webp",
    "mime": "image/webp",
    "wUnits": "px",
    "hUnits": "px",
    "length": 119800,
    "url": "https://cdn.black-clover.org/file/flanbox/failure-frame/chapter-45.2/7.webp"
  },
  {
    "width": 800,
    "height": 1137,
    "type": "webp",
    "mime": "image/webp",
    "wUnits": "px",
    "hUnits": "px",
    "length": 118828,
    "url": "https://cdn.black-clover.org/file/flanbox/failure-frame/chapter-45.2/8.webp"
  },
  {
    "width": 800,
    "height": 1137,
    "type": "webp",
    "mime": "image/webp",
    "wUnits": "px",
    "hUnits": "px",
    "length": 145226,
    "url": "https://cdn.black-clover.org/file/flanbox/failure-frame/chapter-45.2/9.webp"
  },
  {
    "width": 800,
    "height": 1137,
    "type": "webp",
    "mime": "image/webp",
    "wUnits": "px",
    "hUnits": "px",
    "length": 127558,
    "url": "https://cdn.black-clover.org/file/flanbox/failure-frame/chapter-45.2/10.webp"
  },
  {
    "width": 800,
    "height": 1137,
    "type": "webp",
    "mime": "image/webp",
    "wUnits": "px",
    "hUnits": "px",
    "length": 152880,
    "url": "https://cdn.black-clover.org/file/flanbox/failure-frame/chapter-45.2/11.webp"
  },
  {
    "width": 800,
    "height": 1137,
    "type": "webp",
    "mime": "image/webp",
    "wUnits": "px",
    "hUnits": "px",
    "length": 91232,
    "url": "https://cdn.black-clover.org/file/flanbox/failure-frame/chapter-45.2/12.webp"
  },
  {
    "width": 800,
    "height": 1137,
    "type": "webp",
    "mime": "image/webp",
    "wUnits": "px",
    "hUnits": "px",
    "length": 165470,
    "url": "https://cdn.black-clover.org/file/flanbox/failure-frame/chapter-45.2/13.webp"
  },
  {
    "width": 800,
    "height": 1137,
    "type": "webp",
    "mime": "image/webp",
    "wUnits": "px",
    "hUnits": "px",
    "length": 115244,
    "url": "https://cdn.black-clover.org/file/flanbox/failure-frame/chapter-45.2/14.webp"
  },
  {
    "width": 800,
    "height": 1137,
    "type": "webp",
    "mime": "image/webp",
    "wUnits": "px",
    "hUnits": "px",
    "length": 149412,
    "url": "https://cdn.black-clover.org/file/flanbox/failure-frame/chapter-45.2/15.webp"
  },
  {
    "width": 800,
    "height": 1187,
    "type": "webp",
    "mime": "image/webp",
    "wUnits": "px",
    "hUnits": "px",
    "length": 166920,
    "url": "https://cdn.black-clover.org/file/flanbox/failure-frame/chapter-45.2/16.webp"
  }
]